ai_agent/__init__.py
ai_agent/agent.py
ai_agent/entities.py
ai_agent/utils.py
ai_agent/version.py
ai_agent/core/__init__.py
ai_agent/core/core.py
ai_agent/core/abis/__init__.py
ai_agent/core/abis/agent.py
ai_agent/core/abis/manger.py
ai_agent/core/abis/proxy.py
tests/__init__.py
tests/test_agent.py
ai_agent_sdk-1.0.5.dist-info/LICENSE
ai_agent_sdk-1.0.5.dist-info/METADATA
ai_agent_sdk-1.0.5.dist-info/WHEEL
ai_agent_sdk-1.0.5.dist-info/top_level.txt
ai_agent_sdk-1.0.5.dist-info/RECORD
