Metadata-Version: 2.1
Name: ai-agent-sdk
Version: 1.0.5
Summary: ai agent sdk for apro
Home-page: https://github.com/APRO-com/ai-agent-sdk-python
Author: APRO
Author-email: apro@apro.com
Requires-Python: >=3.7, <4
License-File: LICENSE
Requires-Dist: web3 >7.0.0
Requires-Dist: python-dotenv >=1.0.1
Requires-Dist: pytest >=8.0.0
